MANIFEST.in
distribute_setup.py
setup.py
Tic_Tac_Pi.egg-info/PKG-INFO
Tic_Tac_Pi.egg-info/SOURCES.txt
Tic_Tac_Pi.egg-info/dependency_links.txt
Tic_Tac_Pi.egg-info/not-zip-safe
Tic_Tac_Pi.egg-info/requires.txt
Tic_Tac_Pi.egg-info/top_level.txt
gameObjects/Board.py
gameObjects/MenuButton.py
gameObjects/Player.py
gameObjects/TextField.py
gameObjects/TextObject.py
gameObjects/__init__.py