Metadata-Version: 1.1
Name: Tic-Tac-Pi
Version: 0.1.0
Summary: Tic-Tac-Toe between two Raspberry Pis using PyGame
Home-page: https://github.com/mstubinis/Tic-Tac-Pi
Author: mstubinis, Pharas
Author-email: mst6119@rit.edu, bke2759@rit.edu
License: MIT
Keywords: PyGame Python Tic-Tac-Toe
Platform: UNKNOWN
Classifier: Intended Audience :: Other Audience
Classifier: Programming Language :: Python :: 2.7
